<?xml version="1.0" encoding='GB2312'?>
<?xml:stylesheet type="text/xsl" href="table.xsl" ?><Report>
<ReportTitle>C30_1 基线发布报告</ReportTitle>
<RunDate>2001年11月10日 10:44:21</RunDate>
<Parameters>LOOKIN=在LEDS库中; 基线号="C30_1";</Parameters>
<Header>
<Column Label="Element Path" Type="element_pn"/>
</Header>
<Row>
<element_pn>\leds\SQA</element_pn>
</Row>
<Row>
<element_pn>\leds\SQA\LEDS项目SQA计划.doc</element_pn>
</Row>
<Row>
<element_pn>\leds\SQA\RM-需求管理(2001-10-29).xls</element_pn>
</Row>
<Row>
<element_pn>\leds\SQA\SCM-变更流程(2001-10-13).xls</element_pn>
</Row>
<Row>
<element_pn>\leds\SQA\SQA报告（2001-08-15LEDS）.doc</element_pn>
</Row>
<Row>
<element_pn>\leds\SQA\SQA报告（2001-08-24LEDS）.doc</element_pn>
</Row>
<Row>
<element_pn>\leds\SQA\SQA报告（2001-09-11LEDS）.doc</element_pn>
</Row>
<Row>
<element_pn>\leds\SQA\SQA报告（2001-09-14LEDS）.doc</element_pn>
</Row>
<Row>
<element_pn>\leds\SQA\SQA报告（2001-09-29LEDS）.doc</element_pn>
</Row>
<Row>
<element_pn>\leds\SQA\SQA报告（2001-10-13LEDS）.doc</element_pn>
</Row>
<Row>
<element_pn>\leds\SQA\SQA报告（2001-10-15LEDS）.doc</element_pn>
</Row>
<Row>
<element_pn>\leds\SQA\SQA报告（2001-10-23LEDS）.doc</element_pn>
</Row>
<Row>
<element_pn>\leds\SQA\SQA报告（2001-10-29LEDS）.doc</element_pn>
</Row>
<Row>
<element_pn>\leds\SQA\SQA检查表（2001-08-15LEDS）.xls</element_pn>
</Row>
<Row>
<element_pn>\leds\SQA\SQA检查表（2001-08-24LEDS）.xls</element_pn>
</Row>
<Row>
<element_pn>\leds\SQA\SQA检查表（2001-09-11LEDS）.xls</element_pn>
</Row>
<Row>
<element_pn>\leds\SQA\SQA检查表（2001-09-14LEDS）.xls</element_pn>
</Row>
<Row>
<element_pn>\leds\SQA\SQA检查表（2001-10-15LEDS）.xls</element_pn>
</Row>
<Row>
<element_pn>\leds\SQA\SQA检查表（2001-10-23LEDS）.xls</element_pn>
</Row>
<Row>
<element_pn>\leds\SQA\SQA阶段报告(精华迭代一）.doc</element_pn>
</Row>
<Row>
<element_pn>\leds\SQA\TPUP-实施-制定集成计划(2001-09-29).xls</element_pn>
</Row>
<Row>
<element_pn>\leds\标准与指南</element_pn>
</Row>
<Row>
<element_pn>\leds\标准与指南\A业务建模工件集n.zip</element_pn>
</Row>
<Row>
<element_pn>\leds\标准与指南\B需求工件集n.zip</element_pn>
</Row>
<Row>
<element_pn>\leds\标准与指南\CR.doc</element_pn>
</Row>
<Row>
<element_pn>\leds\标准与指南\C分析设计工件集n.zip</element_pn>
</Row>
<Row>
<element_pn>\leds\标准与指南\D实施工件集-实施模型检查表D1.zip</element_pn>
</Row>
<Row>
<element_pn>\leds\标准与指南\E测试工件集.zip</element_pn>
</Row>
<Row>
<element_pn>\leds\标准与指南\F环境工件集- 设计指南检查表F1.zip</element_pn>
</Row>
<Row>
<element_pn>\leds\标准与指南\LEDS-TEST-TG.doc</element_pn>
</Row>
<Row>
<element_pn>\leds\标准与指南\LEDS项目内部正式评审流程的补充.doc</element_pn>
</Row>
<Row>
<element_pn>\leds\标准与指南\工件评审人员角色参考表.doc</element_pn>
</Row>
<Row>
<element_pn>\leds\标准与指南\评审记录表模板.doc</element_pn>
</Row>
<Row>
<element_pn>\leds\标准与指南\评审准备情况表.doc</element_pn>
</Row>
<Row>
<element_pn>\leds\部署</element_pn>
</Row>
<Row>
<element_pn>\leds\部署\LEDS联机帮助文档.doc</element_pn>
</Row>
<Row>
<element_pn>\leds\部署\LED产品清单.doc</element_pn>
</Row>
<Row>
<element_pn>\leds\部署\LED产品用户维护意见反馈卡.doc</element_pn>
</Row>
<Row>
<element_pn>\leds\部署\LED产品注册卡.doc</element_pn>
</Row>
<Row>
<element_pn>\leds\部署\LED托普集团软件产品《使用许可协议》.doc</element_pn>
</Row>
<Row>
<element_pn>\leds\部署\LED用户产品使用意见反馈卡.doc</element_pn>
</Row>
<Row>
<element_pn>\leds\部署\LED用户维护申请单.doc</element_pn>
</Row>
<Row>
<element_pn>\leds\部署\手册风格设计指南.doc</element_pn>
</Row>
<Row>
<element_pn>\leds\测试</element_pn>
</Row>
<Row>
<element_pn>\leds\测试\测试过程</element_pn>
</Row>
<Row>
<element_pn>\leds\测试\测试过程\集成测试过程</element_pn>
</Row>
<Row>
<element_pn>\leds\测试\测试过程\集成测试过程\Build1</element_pn>
</Row>
<Row>
<element_pn>\leds\测试\测试过程\集成测试过程\Build1\LEDS-TEST-SIT-TPR-MakeProgramMenu.doc</element_pn>
</Row>
<Row>
<element_pn>\leds\测试\测试过程\集成测试过程\Build1\LEDS-TEST-SIT-TPR-ManagePlayingPlan.doc</element_pn>
</Row>
<Row>
<element_pn>\leds\测试\测试过程\集成测试过程\Build2</element_pn>
</Row>
<Row>
<element_pn>\leds\测试\测试过程\集成测试过程\Build2\LED-TEST-SIT-TPR-InsertPlaying.doc</element_pn>
</Row>
<Row>
<element_pn>\leds\测试\测试过程\集成测试过程\Build2\LEDS-TEST-SIT-TPR-ControlPlaying.doc</element_pn>
</Row>
<Row>
<element_pn>\leds\测试\测试过程\集成测试过程\Build2\LEDS-TEST-SIT-TPR-TimeControl.doc</element_pn>
</Row>
<Row>
<element_pn>\leds\测试\测试过程\集成测试过程\Build2\LEDS-TEST-SIT-TPR-TimePlaying.doc</element_pn>
</Row>
<Row>
<element_pn>\leds\测试\测试过程\集成测试过程\Build3</element_pn>
</Row>
<Row>
<element_pn>\leds\测试\测试过程\集成测试过程\Build3\LEDS-TEST-SIT-TPR-ConnectLED.doc</element_pn>
</Row>
<Row>
<element_pn>\leds\测试\测试过程\集成测试过程\Build3\LEDS-TEST-SIT-TPR-Login.doc</element_pn>
</Row>
<Row>
<element_pn>\leds\测试\测试过程\集成测试过程\Build3\LEDS-TEST-SIT-TPR-ManageSystem.doc</element_pn>
</Row>
<Row>
<element_pn>\leds\测试\测试过程\集成测试过程\Build3\LEDS-TEST-SIT-TPR-PreviewProgramMenu.doc</element_pn>
</Row>
<Row>
<element_pn>\leds\测试\测试过程\集成测试过程\Build4</element_pn>
</Row>
<Row>
<element_pn>\leds\测试\测试过程\集成测试过程\Build4\LEDS-TEST-SIT-TPR-InformSate.doc</element_pn>
</Row>
<Row>
<element_pn>\leds\测试\测试过程\集成测试过程\Build4\LEDS-TEST-SIT-TPR-ManageLEDState.doc</element_pn>
</Row>
<Row>
<element_pn>\leds\测试\测试过程\系统测试过程</element_pn>
</Row>
<Row>
<element_pn>\leds\测试\测试过程\系统测试过程\LED-TEST-SST-TPR-InsertPlaying.doc</element_pn>
</Row>
<Row>
<element_pn>\leds\测试\测试过程\系统测试过程\LEDS-TEST-SST-TPR-ConnectLED.doc</element_pn>
</Row>
<Row>
<element_pn>\leds\测试\测试过程\系统测试过程\LEDS-TEST-SST-TPR-ControlPlaying.doc</element_pn>
</Row>
<Row>
<element_pn>\leds\测试\测试过程\系统测试过程\LEDS-TEST-SST-TPR-InformState.doc</element_pn>
</Row>
<Row>
<element_pn>\leds\测试\测试过程\系统测试过程\LEDS-TEST-SST-TPR-Login.doc</element_pn>
</Row>
<Row>
<element_pn>\leds\测试\测试过程\系统测试过程\LEDS-TEST-SST-TPR-MakeProgramMenu.doc</element_pn>
</Row>
<Row>
<element_pn>\leds\测试\测试过程\系统测试过程\LEDS-TEST-SST-TPR-ManageLEDState.doc</element_pn>
</Row>
<Row>
<element_pn>\leds\测试\测试过程\系统测试过程\LEDS-TEST-SST-TPR-ManagePlayingLog.doc</element_pn>
</Row>
<Row>
<element_pn>\leds\测试\测试过程\系统测试过程\LEDS-TEST-SST-TPR-ManagePlayingPlan.doc</element_pn>
</Row>
<Row>
<element_pn>\leds\测试\测试过程\系统测试过程\LEDS-TEST-SST-TPR-ManageSystem.doc</element_pn>
</Row>
<Row>
<element_pn>\leds\测试\测试过程\系统测试过程\LEDS-TEST-SST-TPR-ManageWrongLog.doc</element_pn>
</Row>
<Row>
<element_pn>\leds\测试\测试过程\系统测试过程\LEDS-TEST-SST-TPR-PreviewProgramMenu.doc</element_pn>
</Row>
<Row>
<element_pn>\leds\测试\测试过程\系统测试过程\LEDS-TEST-SST-TPR-TimeControl.doc</element_pn>
</Row>
<Row>
<element_pn>\leds\测试\测试过程\系统测试过程\LEDS-TEST-SST-TPR-TimePlaying.doc</element_pn>
</Row>
<Row>
<element_pn>\leds\测试\测试计划</element_pn>
</Row>
<Row>
<element_pn>\leds\测试\测试计划\LEDS-TEST-TP-Integration.doc</element_pn>
</Row>
<Row>
<element_pn>\leds\测试\测试计划\LEDS-TEST-TP-System.doc</element_pn>
</Row>
<Row>
<element_pn>\leds\测试\测试计划\LEDS-TEST-TP.doc</element_pn>
</Row>
<Row>
<element_pn>\leds\测试\测试计划\可测试性报告.doc</element_pn>
</Row>
<Row>
<element_pn>\leds\测试\测试脚本</element_pn>
</Row>
<Row>
<element_pn>\leds\测试\测试结果</element_pn>
</Row>
<Row>
<element_pn>\leds\测试\测试结果\JjcLEDSTPL01.doc</element_pn>
</Row>
<Row>
<element_pn>\leds\测试\测试结果\测试日志-2001-09-28.doc</element_pn>
</Row>
<Row>
<element_pn>\leds\测试\测试结果\测试日志EJCCtlPly01_20010929.doc</element_pn>
</Row>
<Row>
<element_pn>\leds\测试\测试结果\测试日志EJCMkPmMu01_20010928.doc</element_pn>
</Row>
<Row>
<element_pn>\leds\测试\测试结果\测试日志EJCMkPmMu02_20010929.doc</element_pn>
</Row>
<Row>
<element_pn>\leds\测试\测试结果\测试日志EJCMkPmMu03_20010929.doc</element_pn>
</Row>
<Row>
<element_pn>\leds\测试\测试评估</element_pn>
</Row>
<Row>
<element_pn>\leds\测试\测试评估\LEDS Integration Test Evaluation Summary.doc</element_pn>
</Row>
<Row>
<element_pn>\leds\测试\测试评估\LEDS Systest Test Evaluation Summary.doc</element_pn>
</Row>
<Row>
<element_pn>\leds\测试\测试用例</element_pn>
</Row>
<Row>
<element_pn>\leds\测试\测试用例\非功能性测试用例</element_pn>
</Row>
<Row>
<element_pn>\leds\测试\测试用例\非功能性测试用例\LED-TC-Performance.doc</element_pn>
</Row>
<Row>
<element_pn>\leds\测试\测试用例\非功能性测试用例\LEDS-TC-Install.doc</element_pn>
</Row>
<Row>
<element_pn>\leds\测试\测试用例\非功能性测试用例\LEDS-TC-Security.doc</element_pn>
</Row>
<Row>
<element_pn>\leds\测试\测试用例\非功能性测试用例\LEDS-TEST-UFT-TC-Configure.doc</element_pn>
</Row>
<Row>
<element_pn>\leds\测试\测试用例\非功能性测试用例\LEDS-TEST-UFT-TC-GUI.doc</element_pn>
</Row>
<Row>
<element_pn>\leds\测试\测试用例\集成测试用例</element_pn>
</Row>
<Row>
<element_pn>\leds\测试\测试用例\集成测试用例\Build1</element_pn>
</Row>
<Row>
<element_pn>\leds\测试\测试用例\集成测试用例\Build1\LEDS-TEST-SIT-TC-MakeProgramMenu.doc</element_pn>
</Row>
<Row>
<element_pn>\leds\测试\测试用例\集成测试用例\Build1\LEDS-TEST-SIT-TC-ManagePlayingPlan.doc</element_pn>
</Row>
<Row>
<element_pn>\leds\测试\测试用例\集成测试用例\Build2</element_pn>
</Row>
<Row>
<element_pn>\leds\测试\测试用例\集成测试用例\Build2\LEDS-TEST-SIT-TC-ControlPlaying.doc</element_pn>
</Row>
<Row>
<element_pn>\leds\测试\测试用例\集成测试用例\Build2\LEDS-TEST-SIT-TC-InsertPlaying.doc</element_pn>
</Row>
<Row>
<element_pn>\leds\测试\测试用例\集成测试用例\Build2\LEDS-TEST-SIT-TC-TimeControl.doc</element_pn>
</Row>
<Row>
<element_pn>\leds\测试\测试用例\集成测试用例\Build2\LEDS-TEST-SIT-TC-TimePlaying.doc</element_pn>
</Row>
<Row>
<element_pn>\leds\测试\测试用例\集成测试用例\Build3</element_pn>
</Row>
<Row>
<element_pn>\leds\测试\测试用例\集成测试用例\Build3\LEDS-TEST-SIT-TC-ConnectLED.doc</element_pn>
</Row>
<Row>
<element_pn>\leds\测试\测试用例\集成测试用例\Build3\LEDS-TEST-SIT-TC-Login.doc</element_pn>
</Row>
<Row>
<element_pn>\leds\测试\测试用例\集成测试用例\Build3\LEDS-TEST-SIT-TC-ManageSystem.doc</element_pn>
</Row>
<Row>
<element_pn>\leds\测试\测试用例\集成测试用例\Build3\LEDS-TEST-SIT-TC-PreviewProgramMenu.doc</element_pn>
</Row>
<Row>
<element_pn>\leds\测试\测试用例\集成测试用例\Build4</element_pn>
</Row>
<Row>
<element_pn>\leds\测试\测试用例\集成测试用例\Build4\LEDS-TEST-SIT-TC-ConfigureLED.doc</element_pn>
</Row>
<Row>
<element_pn>\leds\测试\测试用例\集成测试用例\Build4\LEDS-TEST-SIT-TC-InformState.doc</element_pn>
</Row>
<Row>
<element_pn>\leds\测试\测试用例\集成测试用例\Build4\LEDS-TEST-SIT-TC-ManageLEDState.doc</element_pn>
</Row>
<Row>
<element_pn>\leds\测试\测试用例\集成测试用例\Build4\LEDS-TEST-SIT-TC-ManagePlayingLog.doc</element_pn>
</Row>
<Row>
<element_pn>\leds\测试\测试用例\集成测试用例\Build4\LEDS-TEST-SIT-TC-ManageWrongLog.doc</element_pn>
</Row>
<Row>
<element_pn>\leds\测试\测试用例\系统测试用例</element_pn>
</Row>
<Row>
<element_pn>\leds\测试\测试用例\系统测试用例\LEDS-TEST-SST-TC-ConfigureLED.doc</element_pn>
</Row>
<Row>
<element_pn>\leds\测试\测试用例\系统测试用例\LEDS-TEST-SST-TC-ConnectLED.doc</element_pn>
</Row>
<Row>
<element_pn>\leds\测试\测试用例\系统测试用例\LEDS-TEST-SST-TC-ControlPlaying.doc</element_pn>
</Row>
<Row>
<element_pn>\leds\测试\测试用例\系统测试用例\LEDS-TEST-SST-TC-InformState.doc</element_pn>
</Row>
<Row>
<element_pn>\leds\测试\测试用例\系统测试用例\LEDS-TEST-SST-TC-InsertPlaying.doc</element_pn>
</Row>
<Row>
<element_pn>\leds\测试\测试用例\系统测试用例\LEDS-TEST-SST-TC-Login.doc</element_pn>
</Row>
<Row>
<element_pn>\leds\测试\测试用例\系统测试用例\LEDS-TEST-SST-TC-MakeDynamicDataMation.doc</element_pn>
</Row>
<Row>
<element_pn>\leds\测试\测试用例\系统测试用例\LEDS-TEST-SST-TC-MakeProgramMenu.doc</element_pn>
</Row>
<Row>
<element_pn>\leds\测试\测试用例\系统测试用例\LEDS-TEST-SST-TC-ManageLEDState.doc</element_pn>
</Row>
<Row>
<element_pn>\leds\测试\测试用例\系统测试用例\LEDS-TEST-SST-TC-ManagePlayingLog.doc</element_pn>
</Row>
<Row>
<element_pn>\leds\测试\测试用例\系统测试用例\LEDS-TEST-SST-TC-ManagePlayingPlan.doc</element_pn>
</Row>
<Row>
<element_pn>\leds\测试\测试用例\系统测试用例\LEDS-TEST-SST-TC-ManageSystem.doc</element_pn>
</Row>
<Row>
<element_pn>\leds\测试\测试用例\系统测试用例\LEDS-TEST-SST-TC-ManageWrongLog.doc</element_pn>
</Row>
<Row>
<element_pn>\leds\测试\测试用例\系统测试用例\LEDS-TEST-SST-TC-PreviewProgramMenu.doc</element_pn>
</Row>
<Row>
<element_pn>\leds\测试\测试用例\系统测试用例\LEDS-TEST-SST-TC-TimeControl.doc</element_pn>
</Row>
<Row>
<element_pn>\leds\测试\测试用例\系统测试用例\LEDS-TEST-SST-TC-TimePlaying.doc</element_pn>
</Row>
<Row>
<element_pn>\leds\测试\测试指南</element_pn>
</Row>
<Row>
<element_pn>\leds\测试\测试指南\LEDS-TEST-TG.doc</element_pn>
</Row>
<Row>
<element_pn>\leds\代码</element_pn>
</Row>
<Row>
<element_pn>\leds\代码\CommLib</element_pn>
</Row>
<Row>
<element_pn>\leds\代码\CommLib\GetFile.cpp</element_pn>
</Row>
<Row>
<element_pn>\leds\代码\CommLib\GetFile.h</element_pn>
</Row>
<Row>
<element_pn>\leds\代码\CommLib\LEDClientSocketHWND.cpp</element_pn>
</Row>
<Row>
<element_pn>\leds\代码\CommLib\LEDClientSocketHWND.h</element_pn>
</Row>
<Row>
<element_pn>\leds\代码\CommLib\LEDServerSocketHWND.cpp</element_pn>
</Row>
<Row>
<element_pn>\leds\代码\CommLib\LEDServerSocketHWND.h</element_pn>
</Row>
<Row>
<element_pn>\leds\代码\CommLib\LEDSocket.cpp</element_pn>
</Row>
<Row>
<element_pn>\leds\代码\CommLib\LEDSocket.h</element_pn>
</Row>
<Row>
<element_pn>\leds\代码\CommLib\m_ledcomm.h</element_pn>
</Row>
<Row>
<element_pn>\leds\代码\CommLib\MasterComm.cpp</element_pn>
</Row>
<Row>
<element_pn>\leds\代码\CommLib\MasterComm.h</element_pn>
</Row>
<Row>
<element_pn>\leds\代码\CommLib\MasterWndPro.cpp</element_pn>
</Row>
<Row>
<element_pn>\leds\代码\CommLib\SendFile.cpp</element_pn>
</Row>
<Row>
<element_pn>\leds\代码\CommLib\sendfile.h</element_pn>
</Row>
<Row>
<element_pn>\leds\代码\CommLib\SlaveComm.cpp</element_pn>
</Row>
<Row>
<element_pn>\leds\代码\CommLib\SlaveComm.h</element_pn>
</Row>
<Row>
<element_pn>\leds\代码\CommLib\SlavewndPro.cpp</element_pn>
</Row>
<Row>
<element_pn>\leds\代码\Core</element_pn>
</Row>
<Row>
<element_pn>\leds\代码\Core\ActiveX</element_pn>
</Row>
<Row>
<element_pn>\leds\代码\Core\ActiveX\cell32.ocx</element_pn>
</Row>
<Row>
<element_pn>\leds\代码\Core\ControlPlaying</element_pn>
</Row>
<Row>
<element_pn>\leds\代码\Core\ControlPlaying\CControlPlayingControl.cpp</element_pn>
</Row>
<Row>
<element_pn>\leds\代码\Core\ControlPlaying\CControlPlayingControl.h</element_pn>
</Row>
<Row>
<element_pn>\leds\代码\Core\global</element_pn>
</Row>
<Row>
<element_pn>\leds\代码\Core\global\Global.h</element_pn>
</Row>
<Row>
<element_pn>\leds\代码\Core\InsertPlaying</element_pn>
</Row>
<Row>
<element_pn>\leds\代码\Core\InsertPlaying\InsertPlayingControl.cpp</element_pn>
</Row>
<Row>
<element_pn>\leds\代码\Core\InsertPlaying\InsertPlayingControl.h</element_pn>
</Row>
<Row>
<element_pn>\leds\代码\Core\LedSet</element_pn>
</Row>
<Row>
<element_pn>\leds\代码\Core\LedSet\LedSet.cpp</element_pn>
</Row>
<Row>
<element_pn>\leds\代码\Core\LedSet\LedSet.h</element_pn>
</Row>
<Row>
<element_pn>\leds\代码\Core\PlayPlan</element_pn>
</Row>
<Row>
<element_pn>\leds\代码\Core\PlayPlan\PlayingItemSink.cpp</element_pn>
</Row>
<Row>
<element_pn>\leds\代码\Core\PlayPlan\PlayingItemSink.h</element_pn>
</Row>
<Row>
<element_pn>\leds\代码\Core\PlayPlan\PlayingPlanForMake.cpp</element_pn>
</Row>
<Row>
<element_pn>\leds\代码\Core\PlayPlan\PlayingPlanForMake.h</element_pn>
</Row>
<Row>
<element_pn>\leds\代码\Core\PlayPlan\PlayingPlanForPlay.cpp</element_pn>
</Row>
<Row>
<element_pn>\leds\代码\Core\PlayPlan\PlayingPlanForPlay.h</element_pn>
</Row>
<Row>
<element_pn>\leds\代码\Core\PlayPlan\PlayItem.cpp</element_pn>
</Row>
<Row>
<element_pn>\leds\代码\Core\PlayPlan\PlayItem.h</element_pn>
</Row>
<Row>
<element_pn>\leds\代码\Core\ProGramMenu</element_pn>
</Row>
<Row>
<element_pn>\leds\代码\Core\ProGramMenu\Program.cpp</element_pn>
</Row>
<Row>
<element_pn>\leds\代码\Core\ProGramMenu\Program.h</element_pn>
</Row>
<Row>
<element_pn>\leds\代码\Core\ProGramMenu\ProgramMenuForMake.cpp</element_pn>
</Row>
<Row>
<element_pn>\leds\代码\Core\ProGramMenu\ProgramMenuForMake.h</element_pn>
</Row>
<Row>
<element_pn>\leds\代码\Core\ProGramMenu\ProgramMenuForPlay.cpp</element_pn>
</Row>
<Row>
<element_pn>\leds\代码\Core\ProGramMenu\ProgramMenuForPlay.h</element_pn>
</Row>
<Row>
<element_pn>\leds\代码\Core\ProGramMenu\ProgramMenuForPreview.cpp</element_pn>
</Row>
<Row>
<element_pn>\leds\代码\Core\SystemClock</element_pn>
</Row>
<Row>
<element_pn>\leds\代码\Core\SystemClock\Clock.cpp</element_pn>
</Row>
<Row>
<element_pn>\leds\代码\Core\SystemClock\Clock.h</element_pn>
</Row>
<Row>
<element_pn>\leds\代码\Core\SystemClock\LedTimerStuct.cpp</element_pn>
</Row>
<Row>
<element_pn>\leds\代码\Core\SystemClock\LedTimerStuct.h</element_pn>
</Row>
<Row>
<element_pn>\leds\代码\Core\SystemInfo</element_pn>
</Row>
<Row>
<element_pn>\leds\代码\Core\SystemInfo\LEDClientData.cpp</element_pn>
</Row>
<Row>
<element_pn>\leds\代码\Core\SystemInfo\LEDClientData.h</element_pn>
</Row>
<Row>
<element_pn>\leds\代码\Core\SystemInfo\RegClient.cpp</element_pn>
</Row>
<Row>
<element_pn>\leds\代码\Core\SystemInfo\RegClient.h</element_pn>
</Row>
<Row>
<element_pn>\leds\代码\Core\SystemInfo\tagUser.h</element_pn>
</Row>
<Row>
<element_pn>\leds\代码\Core\SystemInfo\UserData.cpp</element_pn>
</Row>
<Row>
<element_pn>\leds\代码\Core\SystemInfo\UserData.h</element_pn>
</Row>
<Row>
<element_pn>\leds\代码\Player Subsystem</element_pn>
</Row>
<Row>
<element_pn>\leds\代码\Player Subsystem\AgifPlayer.cpp</element_pn>
</Row>
<Row>
<element_pn>\leds\代码\Player Subsystem\AgifPlayer.h</element_pn>
</Row>
<Row>
<element_pn>\leds\代码\Player Subsystem\AgifPlayWnd.cpp</element_pn>
</Row>
<Row>
<element_pn>\leds\代码\Player Subsystem\AgifPlayWnd.h</element_pn>
</Row>
<Row>
<element_pn>\leds\代码\Player Subsystem\anigif.cpp</element_pn>
</Row>
<Row>
<element_pn>\leds\代码\Player Subsystem\anigif.h</element_pn>
</Row>
<Row>
<element_pn>\leds\代码\Player Subsystem\FlashPlayWnd.cpp</element_pn>
</Row>
<Row>
<element_pn>\leds\代码\Player Subsystem\FlashPlayWnd.h</element_pn>
</Row>
<Row>
<element_pn>\leds\代码\Player Subsystem\FlcPlayer.cpp</element_pn>
</Row>
<Row>
<element_pn>\leds\代码\Player Subsystem\FlcPlayer.h</element_pn>
</Row>
<Row>
<element_pn>\leds\代码\Player Subsystem\FlcPlayWnd.cpp</element_pn>
</Row>
<Row>
<element_pn>\leds\代码\Player Subsystem\FlcPlayWnd.h</element_pn>
</Row>
<Row>
<element_pn>\leds\代码\Player Subsystem\masflcplayer.cpp</element_pn>
</Row>
<Row>
<element_pn>\leds\代码\Player Subsystem\masflcplayer.h</element_pn>
</Row>
<Row>
<element_pn>\leds\代码\Player Subsystem\mediaplayer2.cpp</element_pn>
</Row>
<Row>
<element_pn>\leds\代码\Player Subsystem\mediaplayer2.h</element_pn>
</Row>
<Row>
<element_pn>\leds\代码\Player Subsystem\mediaplayerdvd.cpp</element_pn>
</Row>
<Row>
<element_pn>\leds\代码\Player Subsystem\mediaplayerdvd.h</element_pn>
</Row>
<Row>
<element_pn>\leds\代码\Player Subsystem\PicPlayer.cpp</element_pn>
</Row>
<Row>
<element_pn>\leds\代码\Player Subsystem\PicPlayer.h</element_pn>
</Row>
<Row>
<element_pn>\leds\代码\Player Subsystem\PicPlayWnd.cpp</element_pn>
</Row>
<Row>
<element_pn>\leds\代码\Player Subsystem\PicPlayWnd.h</element_pn>
</Row>
<Row>
<element_pn>\leds\代码\Player Subsystem\picture.cpp</element_pn>
</Row>
<Row>
<element_pn>\leds\代码\Player Subsystem\picture.h</element_pn>
</Row>
<Row>
<element_pn>\leds\代码\Player Subsystem\PlayAVIDialog.cpp</element_pn>
</Row>
<Row>
<element_pn>\leds\代码\Player Subsystem\PlayAVIDialog.h</element_pn>
</Row>
<Row>
<element_pn>\leds\代码\Player Subsystem\PlayFlashDialog.cpp</element_pn>
</Row>
<Row>
<element_pn>\leds\代码\Player Subsystem\PlayFlashDialog.h</element_pn>
</Row>
<Row>
<element_pn>\leds\代码\Player Subsystem\Program.cpp</element_pn>
</Row>
<Row>
<element_pn>\leds\代码\Player Subsystem\Program.h</element_pn>
</Row>
<Row>
<element_pn>\leds\代码\Player Subsystem\ReportPlayer.cpp</element_pn>
</Row>
<Row>
<element_pn>\leds\代码\Player Subsystem\ReportPlayer.h</element_pn>
</Row>
<Row>
<element_pn>\leds\代码\Player Subsystem\ReportPlayWnd.cpp</element_pn>
</Row>
<Row>
<element_pn>\leds\代码\Player Subsystem\ReportPlayWnd.h</element_pn>
</Row>
<Row>
<element_pn>\leds\代码\Player Subsystem\resource.h</element_pn>
</Row>
<Row>
<element_pn>\leds\代码\Player Subsystem\Script1.rc</element_pn>
</Row>
<Row>
<element_pn>\leds\代码\Player Subsystem\shockwaveflash.cpp</element_pn>
</Row>
<Row>
<element_pn>\leds\代码\Player Subsystem\shockwaveflash.h</element_pn>
</Row>
<Row>
<element_pn>\leds\代码\Player Subsystem\SvideoPlayer.cpp</element_pn>
</Row>
<Row>
<element_pn>\leds\代码\Player Subsystem\SvideoPlayer.h</element_pn>
</Row>
<Row>
<element_pn>\leds\代码\Player Subsystem\SvideoPlayWnd.cpp</element_pn>
</Row>
<Row>
<element_pn>\leds\代码\Player Subsystem\SvideoPlayWnd.h</element_pn>
</Row>
<Row>
<element_pn>\leds\代码\Player Subsystem\TextPlayer.cpp</element_pn>
</Row>
<Row>
<element_pn>\leds\代码\Player Subsystem\TextPlayer.h</element_pn>
</Row>
<Row>
<element_pn>\leds\代码\Player Subsystem\TextPlayWnd.cpp</element_pn>
</Row>
<Row>
<element_pn>\leds\代码\Player Subsystem\TextPlayWnd.h</element_pn>
</Row>
<Row>
<element_pn>\leds\代码\Player Subsystem\VideoPlayer.cpp</element_pn>
</Row>
<Row>
<element_pn>\leds\代码\Player Subsystem\VideoPlayer.h</element_pn>
</Row>
<Row>
<element_pn>\leds\代码\Player Subsystem\VideoPlayWnd.cpp</element_pn>
</Row>
<Row>
<element_pn>\leds\代码\Player Subsystem\VideoPlayWnd.h</element_pn>
</Row>
<Row>
<element_pn>\leds\代码\Product</element_pn>
</Row>
<Row>
<element_pn>\leds\代码\Product\MastorForm</element_pn>
</Row>
<Row>
<element_pn>\leds\代码\Product\MastorForm\AddProgramMenu.cpp</element_pn>
</Row>
<Row>
<element_pn>\leds\代码\Product\MastorForm\AddProgramMenu.h</element_pn>
</Row>
<Row>
<element_pn>\leds\代码\Product\MastorForm\BtnST.cpp</element_pn>
</Row>
<Row>
<element_pn>\leds\代码\Product\MastorForm\BtnST.h</element_pn>
</Row>
<Row>
<element_pn>\leds\代码\Product\MastorForm\cell.cpp</element_pn>
</Row>
<Row>
<element_pn>\leds\代码\Product\MastorForm\cell.h</element_pn>
</Row>
<Row>
<element_pn>\leds\代码\Product\MastorForm\ChildFrm.cpp</element_pn>
</Row>
<Row>
<element_pn>\leds\代码\Product\MastorForm\ChildFrm.h</element_pn>
</Row>
<Row>
<element_pn>\leds\代码\Product\MastorForm\CommLib.lib</element_pn>
</Row>
<Row>
<element_pn>\leds\代码\Product\MastorForm\ConfigUseLedForm.cpp</element_pn>
</Row>
<Row>
<element_pn>\leds\代码\Product\MastorForm\ConfigUseLedForm.h</element_pn>
</Row>
<Row>
<element_pn>\leds\代码\Product\MastorForm\ConfigUserLEDForm.cpp</element_pn>
</Row>
<Row>
<element_pn>\leds\代码\Product\MastorForm\ControlPlayForm.cpp</element_pn>
</Row>
<Row>
<element_pn>\leds\代码\Product\MastorForm\ControlPlayForm.h</element_pn>
</Row>
<Row>
<element_pn>\leds\代码\Product\MastorForm\Debug</element_pn>
</Row>
<Row>
<element_pn>\leds\代码\Product\MastorForm\DialogLEDRegist.cpp</element_pn>
</Row>
<Row>
<element_pn>\leds\代码\Product\MastorForm\DialogLEDRegist.h</element_pn>
</Row>
<Row>
<element_pn>\leds\代码\Product\MastorForm\EditPlayPlanForm.cpp</element_pn>
</Row>
<Row>
<element_pn>\leds\代码\Product\MastorForm\EditPlayPlanForm.h</element_pn>
</Row>
<Row>
<element_pn>\leds\代码\Product\MastorForm\GfxGroupEdit.cpp</element_pn>
</Row>
<Row>
<element_pn>\leds\代码\Product\MastorForm\GfxGroupEdit.h</element_pn>
</Row>
<Row>
<element_pn>\leds\代码\Product\MastorForm\GfxOutBarCtrl.cpp</element_pn>
</Row>
<Row>
<element_pn>\leds\代码\Product\MastorForm\GfxOutBarCtrl.h</element_pn>
</Row>
<Row>
<element_pn>\leds\代码\Product\MastorForm\GfxPopupMenu.cpp</element_pn>
</Row>
<Row>
<element_pn>\leds\代码\Product\MastorForm\GfxPopupMenu.h</element_pn>
</Row>
<Row>
<element_pn>\leds\代码\Product\MastorForm\GfxSplitterWnd.cpp</element_pn>
</Row>
<Row>
<element_pn>\leds\代码\Product\MastorForm\GfxSplitterWnd.h</element_pn>
</Row>
<Row>
<element_pn>\leds\代码\Product\MastorForm\InsertPlayForm.cpp</element_pn>
</Row>
<Row>
<element_pn>\leds\代码\Product\MastorForm\InsertPlayForm.h</element_pn>
</Row>
<Row>
<element_pn>\leds\代码\Product\MastorForm\LEDClientData.cpp</element_pn>
</Row>
<Row>
<element_pn>\leds\代码\Product\MastorForm\LEDClientData.h</element_pn>
</Row>
<Row>
<element_pn>\leds\代码\Product\MastorForm\LEDS.APS</element_pn>
</Row>
<Row>
<element_pn>\leds\代码\Product\MastorForm\LEDS.clw</element_pn>
</Row>
<Row>
<element_pn>\leds\代码\Product\MastorForm\LEDS.cpp</element_pn>
</Row>
<Row>
<element_pn>\leds\代码\Product\MastorForm\LEDS.dsp</element_pn>
</Row>
<Row>
<element_pn>\leds\代码\Product\MastorForm\LEDS.dsw</element_pn>
</Row>
<Row>
<element_pn>\leds\代码\Product\MastorForm\LEDS.h</element_pn>
</Row>
<Row>
<element_pn>\leds\代码\Product\MastorForm\LEDS.ncb</element_pn>
</Row>
<Row>
<element_pn>\leds\代码\Product\MastorForm\LEDS.opt</element_pn>
</Row>
<Row>
<element_pn>\leds\代码\Product\MastorForm\LEDS.plg</element_pn>
</Row>
<Row>
<element_pn>\leds\代码\Product\MastorForm\LEDS.rc</element_pn>
</Row>
<Row>
<element_pn>\leds\代码\Product\MastorForm\LEDSDoc.cpp</element_pn>
</Row>
<Row>
<element_pn>\leds\代码\Product\MastorForm\LEDSDoc.h</element_pn>
</Row>
<Row>
<element_pn>\leds\代码\Product\MastorForm\LEDSocket.h</element_pn>
</Row>
<Row>
<element_pn>\leds\代码\Product\MastorForm\listctrlex.cpp</element_pn>
</Row>
<Row>
<element_pn>\leds\代码\Product\MastorForm\listctrlex.h</element_pn>
</Row>
<Row>
<element_pn>\leds\代码\Product\MastorForm\LoginDialog.cpp</element_pn>
</Row>
<Row>
<element_pn>\leds\代码\Product\MastorForm\LoginDialog.h</element_pn>
</Row>
<Row>
<element_pn>\leds\代码\Product\MastorForm\MainFrm.cpp</element_pn>
</Row>
<Row>
<element_pn>\leds\代码\Product\MastorForm\MainFrm.h</element_pn>
</Row>
<Row>
<element_pn>\leds\代码\Product\MastorForm\ManageClientForm.cpp</element_pn>
</Row>
<Row>
<element_pn>\leds\代码\Product\MastorForm\ManageClientForm.h</element_pn>
</Row>
<Row>
<element_pn>\leds\代码\Product\MastorForm\ManagePlayLogForm.cpp</element_pn>
</Row>
<Row>
<element_pn>\leds\代码\Product\MastorForm\ManagePlayLogForm.h</element_pn>
</Row>
<Row>
<element_pn>\leds\代码\Product\MastorForm\ManageUserForm.cpp</element_pn>
</Row>
<Row>
<element_pn>\leds\代码\Product\MastorForm\ManageUserForm.h</element_pn>
</Row>
<Row>
<element_pn>\leds\代码\Product\MastorForm\ManageWrongLogForm.cpp</element_pn>
</Row>
<Row>
<element_pn>\leds\代码\Product\MastorForm\ManageWrongLogForm.h</element_pn>
</Row>
<Row>
<element_pn>\leds\代码\Product\MastorForm\Masked.cpp</element_pn>
</Row>
<Row>
<element_pn>\leds\代码\Product\MastorForm\Masked.h</element_pn>
</Row>
<Row>
<element_pn>\leds\代码\Product\MastorForm\PlayandPlan</element_pn>
</Row>
<Row>
<element_pn>\leds\代码\Product\MastorForm\PlayandPlan\CControlPlayingControl.cpp</element_pn>
</Row>
<Row>
<element_pn>\leds\代码\Product\MastorForm\PlayandPlan\CControlPlayingControl.h</element_pn>
</Row>
<Row>
<element_pn>\leds\代码\Product\MastorForm\PlayandPlan\PlayingItemSink.cpp</element_pn>
</Row>
<Row>
<element_pn>\leds\代码\Product\MastorForm\PlayandPlan\PlayingItemSink.h</element_pn>
</Row>
<Row>
<element_pn>\leds\代码\Product\MastorForm\PlayandPlan\PlayingPlan.cpp</element_pn>
</Row>
<Row>
<element_pn>\leds\代码\Product\MastorForm\PlayandPlan\PlayingPlan.h</element_pn>
</Row>
<Row>
<element_pn>\leds\代码\Product\MastorForm\PlayandPlan\PlayItem.cpp</element_pn>
</Row>
<Row>
<element_pn>\leds\代码\Product\MastorForm\PlayandPlan\PlayItem.h</element_pn>
</Row>
<Row>
<element_pn>\leds\代码\Product\MastorForm\PutInPlayPlanForm.cpp</element_pn>
</Row>
<Row>
<element_pn>\leds\代码\Product\MastorForm\PutInPlayPlanForm.h</element_pn>
</Row>
<Row>
<element_pn>\leds\代码\Product\MastorForm\ReadMe.txt</element_pn>
</Row>
<Row>
<element_pn>\leds\代码\Product\MastorForm\RegClient.cpp</element_pn>
</Row>
<Row>
<element_pn>\leds\代码\Product\MastorForm\RegClient.h</element_pn>
</Row>
<Row>
<element_pn>\leds\代码\Product\MastorForm\res</element_pn>
</Row>
<Row>
<element_pn>\leds\代码\Product\MastorForm\resource.h</element_pn>
</Row>
<Row>
<element_pn>\leds\代码\Product\MastorForm\StdAfx.cpp</element_pn>
</Row>
<Row>
<element_pn>\leds\代码\Product\MastorForm\StdAfx.h</element_pn>
</Row>
<Row>
<element_pn>\leds\代码\Product\MastorForm\TitleTip.cpp</element_pn>
</Row>
<Row>
<element_pn>\leds\代码\Product\MastorForm\TitleTip.h</element_pn>
</Row>
<Row>
<element_pn>\leds\代码\Product\MastorForm\UserDlg.cpp</element_pn>
</Row>
<Row>
<element_pn>\leds\代码\Product\MastorForm\UserDlg.h</element_pn>
</Row>
<Row>
<element_pn>\leds\代码\Product\MastorForm\WelcomeDialog.cpp</element_pn>
</Row>
<Row>
<element_pn>\leds\代码\Product\MastorForm\WelcomeDialog.h</element_pn>
</Row>
<Row>
<element_pn>\leds\代码\Product\PreviewMenu</element_pn>
</Row>
<Row>
<element_pn>\leds\代码\Product\PreviewMenu\backbmp.bmp</element_pn>
</Row>
<Row>
<element_pn>\leds\代码\Product\PreviewMenu\Backbmp_Preview.bmp</element_pn>
</Row>
<Row>
<element_pn>\leds\代码\Product\PreviewMenu\Forebmp.bmp</element_pn>
</Row>
<Row>
<element_pn>\leds\代码\Product\PreviewMenu\Forebmp_Preview.bmp</element_pn>
</Row>
<Row>
<element_pn>\leds\代码\Product\PreviewMenu\gg.cur</element_pn>
</Row>
<Row>
<element_pn>\leds\代码\Product\PreviewMenu\Global.h</element_pn>
</Row>
<Row>
<element_pn>\leds\代码\Product\PreviewMenu\Hand.cur</element_pn>
</Row>
<Row>
<element_pn>\leds\代码\Product\PreviewMenu\Hotspot.cpp</element_pn>
</Row>
<Row>
<element_pn>\leds\代码\Product\PreviewMenu\Hotspot.h</element_pn>
</Row>
<Row>
<element_pn>\leds\代码\Product\PreviewMenu\HOTSPOT4.EXE</element_pn>
</Row>
<Row>
<element_pn>\leds\代码\Product\PreviewMenu\MyBmp.cpp</element_pn>
</Row>
<Row>
<element_pn>\leds\代码\Product\PreviewMenu\MyBmp.h</element_pn>
</Row>
<Row>
<element_pn>\leds\代码\Product\PreviewMenu\PlayerInterface.h</element_pn>
</Row>
<Row>
<element_pn>\leds\代码\Product\PreviewMenu\PlaySystem.lib</element_pn>
</Row>
<Row>
<element_pn>\leds\代码\Product\PreviewMenu\POLYHOTS.DAT</element_pn>
</Row>
<Row>
<element_pn>\leds\代码\Product\PreviewMenu\Polyhots_Preview.dat</element_pn>
</Row>
<Row>
<element_pn>\leds\代码\Product\PreviewMenu\PreviewMenu.aps</element_pn>
</Row>
<Row>
<element_pn>\leds\代码\Product\PreviewMenu\PreviewMenu.clw</element_pn>
</Row>
<Row>
<element_pn>\leds\代码\Product\PreviewMenu\PreviewMenu.cpp</element_pn>
</Row>
<Row>
<element_pn>\leds\代码\Product\PreviewMenu\PreviewMenu.dsp</element_pn>
</Row>
<Row>
<element_pn>\leds\代码\Product\PreviewMenu\PreviewMenu.dsw</element_pn>
</Row>
<Row>
<element_pn>\leds\代码\Product\PreviewMenu\PreviewMenu.h</element_pn>
</Row>
<Row>
<element_pn>\leds\代码\Product\PreviewMenu\PreviewMenu.ncb</element_pn>
</Row>
<Row>
<element_pn>\leds\代码\Product\PreviewMenu\PreviewMenu.opt</element_pn>
</Row>
<Row>
<element_pn>\leds\代码\Product\PreviewMenu\PreviewMenu.plg</element_pn>
</Row>
<Row>
<element_pn>\leds\代码\Product\PreviewMenu\PreviewMenu.rc</element_pn>
</Row>
<Row>
<element_pn>\leds\代码\Product\PreviewMenu\PreviewMenuDlg.cpp</element_pn>
</Row>
<Row>
<element_pn>\leds\代码\Product\PreviewMenu\PreviewMenuDlg.h</element_pn>
</Row>
<Row>
<element_pn>\leds\代码\Product\PreviewMenu\Program.cpp</element_pn>
</Row>
<Row>
<element_pn>\leds\代码\Product\PreviewMenu\Program.h</element_pn>
</Row>
<Row>
<element_pn>\leds\代码\Product\PreviewMenu\ProgramMenu.h</element_pn>
</Row>
<Row>
<element_pn>\leds\代码\Product\PreviewMenu\ProgramMenuForPreview.cpp</element_pn>
</Row>
<Row>
<element_pn>\leds\代码\Product\PreviewMenu\ReadMe.txt</element_pn>
</Row>
<Row>
<element_pn>\leds\代码\Product\PreviewMenu\res</element_pn>
</Row>
<Row>
<element_pn>\leds\代码\Product\PreviewMenu\resource.h</element_pn>
</Row>
<Row>
<element_pn>\leds\代码\Product\PreviewMenu\StdAfx.cpp</element_pn>
</Row>
<Row>
<element_pn>\leds\代码\Product\PreviewMenu\StdAfx.h</element_pn>
</Row>
<Row>
<element_pn>\leds\代码\Product\PreviewMenu\SYS.ICO</element_pn>
</Row>
<Row>
<element_pn>\leds\代码\Product\PreviewMenu\WndRectDlg.cpp</element_pn>
</Row>
<Row>
<element_pn>\leds\代码\Product\PreviewMenu\WndRectDlg.h</element_pn>
</Row>
<Row>
<element_pn>\leds\代码\Product\SlaveForm</element_pn>
</Row>
<Row>
<element_pn>\leds\代码\Product\SlaveForm\CControlPlayingControl.cpp</element_pn>
</Row>
<Row>
<element_pn>\leds\代码\Product\SlaveForm\CControlPlayingControl.h</element_pn>
</Row>
<Row>
<element_pn>\leds\代码\Product\SlaveForm\Clock.cpp</element_pn>
</Row>
<Row>
<element_pn>\leds\代码\Product\SlaveForm\Clock.h</element_pn>
</Row>
<Row>
<element_pn>\leds\代码\Product\SlaveForm\CommLib.lib</element_pn>
</Row>
<Row>
<element_pn>\leds\代码\Product\SlaveForm\default.pln</element_pn>
</Row>
<Row>
<element_pn>\leds\代码\Product\SlaveForm\gg.cur</element_pn>
</Row>
<Row>
<element_pn>\leds\代码\Product\SlaveForm\Global.h</element_pn>
</Row>
<Row>
<element_pn>\leds\代码\Product\SlaveForm\Hand.cur</element_pn>
</Row>
<Row>
<element_pn>\leds\代码\Product\SlaveForm\Hotspot.cpp</element_pn>
</Row>
<Row>
<element_pn>\leds\代码\Product\SlaveForm\Hotspot.h</element_pn>
</Row>
<Row>
<element_pn>\leds\代码\Product\SlaveForm\InsertPlayDlg.cpp</element_pn>
</Row>
<Row>
<element_pn>\leds\代码\Product\SlaveForm\InsertPlayDlg.h</element_pn>
</Row>
<Row>
<element_pn>\leds\代码\Product\SlaveForm\InsertPlayingControl.cpp</element_pn>
</Row>
<Row>
<element_pn>\leds\代码\Product\SlaveForm\InsertPlayingControl.h</element_pn>
</Row>
<Row>
<element_pn>\leds\代码\Product\SlaveForm\LEDClientSocketHWND.h</element_pn>
</Row>
<Row>
<element_pn>\leds\代码\Product\SlaveForm\ledlog.mdb</element_pn>
</Row>
<Row>
<element_pn>\leds\代码\Product\SlaveForm\LEDS.APS</element_pn>
</Row>
<Row>
<element_pn>\leds\代码\Product\SlaveForm\LEDS.clw</element_pn>
</Row>
<Row>
<element_pn>\leds\代码\Product\SlaveForm\LEDS.cpp</element_pn>
</Row>
<Row>
<element_pn>\leds\代码\Product\SlaveForm\LEDS.dsp</element_pn>
</Row>
<Row>
<element_pn>\leds\代码\Product\SlaveForm\LEDS.dsw</element_pn>
</Row>
<Row>
<element_pn>\leds\代码\Product\SlaveForm\LEDS.h</element_pn>
</Row>
<Row>
<element_pn>\leds\代码\Product\SlaveForm\LEDS.ncb</element_pn>
</Row>
<Row>
<element_pn>\leds\代码\Product\SlaveForm\LEDS.opt</element_pn>
</Row>
<Row>
<element_pn>\leds\代码\Product\SlaveForm\LEDS.plg</element_pn>
</Row>
<Row>
<element_pn>\leds\代码\Product\SlaveForm\LEDS.rc</element_pn>
</Row>
<Row>
<element_pn>\leds\代码\Product\SlaveForm\LEDSDlg.cpp</element_pn>
</Row>
<Row>
<element_pn>\leds\代码\Product\SlaveForm\LEDSDlg.h</element_pn>
</Row>
<Row>
<element_pn>\leds\代码\Product\SlaveForm\LEDServerSocketHWND.h</element_pn>
</Row>
<Row>
<element_pn>\leds\代码\Product\SlaveForm\LedSet.cpp</element_pn>
</Row>
<Row>
<element_pn>\leds\代码\Product\SlaveForm\LedSet.h</element_pn>
</Row>
<Row>
<element_pn>\leds\代码\Product\SlaveForm\LEDSocket.h</element_pn>
</Row>
<Row>
<element_pn>\leds\代码\Product\SlaveForm\LedTimerStuct.cpp</element_pn>
</Row>
<Row>
<element_pn>\leds\代码\Product\SlaveForm\LedTimerStuct.h</element_pn>
</Row>
<Row>
<element_pn>\leds\代码\Product\SlaveForm\Log.cpp</element_pn>
</Row>
<Row>
<element_pn>\leds\代码\Product\SlaveForm\Log.h</element_pn>
</Row>
<Row>
<element_pn>\leds\代码\Product\SlaveForm\m_ledcomm.h</element_pn>
</Row>
<Row>
<element_pn>\leds\代码\Product\SlaveForm\mssccprj.scc</element_pn>
</Row>
<Row>
<element_pn>\leds\代码\Product\SlaveForm\MyBmp.cpp</element_pn>
</Row>
<Row>
<element_pn>\leds\代码\Product\SlaveForm\MyBmp.h</element_pn>
</Row>
<Row>
<element_pn>\leds\代码\Product\SlaveForm\PlayerInterface.h</element_pn>
</Row>
<Row>
<element_pn>\leds\代码\Product\SlaveForm\PlayingItemSink.cpp</element_pn>
</Row>
<Row>
<element_pn>\leds\代码\Product\SlaveForm\PlayingItemSink.h</element_pn>
</Row>
<Row>
<element_pn>\leds\代码\Product\SlaveForm\PlayingPlan.cpp</element_pn>
</Row>
<Row>
<element_pn>\leds\代码\Product\SlaveForm\PlayingPlan.h</element_pn>
</Row>
<Row>
<element_pn>\leds\代码\Product\SlaveForm\PlayItem.cpp</element_pn>
</Row>
<Row>
<element_pn>\leds\代码\Product\SlaveForm\PlayItem.h</element_pn>
</Row>
<Row>
<element_pn>\leds\代码\Product\SlaveForm\PlaySystem.lib</element_pn>
</Row>
<Row>
<element_pn>\leds\代码\Product\SlaveForm\PLogRecordset.cpp</element_pn>
</Row>
<Row>
<element_pn>\leds\代码\Product\SlaveForm\PLogRecordset.h</element_pn>
</Row>
<Row>
<element_pn>\leds\代码\Product\SlaveForm\Program.cpp</element_pn>
</Row>
<Row>
<element_pn>\leds\代码\Product\SlaveForm\Program.h</element_pn>
</Row>
<Row>
<element_pn>\leds\代码\Product\SlaveForm\ProgramMenu.h</element_pn>
</Row>
<Row>
<element_pn>\leds\代码\Product\SlaveForm\ProgramMenuForPlay.cpp</element_pn>
</Row>
<Row>
<element_pn>\leds\代码\Product\SlaveForm\ReadMe.txt</element_pn>
</Row>
<Row>
<element_pn>\leds\代码\Product\SlaveForm\res</element_pn>
</Row>
<Row>
<element_pn>\leds\代码\Product\SlaveForm\res\LEDS.ico</element_pn>
</Row>
<Row>
<element_pn>\leds\代码\Product\SlaveForm\res\LEDS.rc2</element_pn>
</Row>
<Row>
<element_pn>\leds\代码\Product\SlaveForm\res\vssver.scc</element_pn>
</Row>
<Row>
<element_pn>\leds\代码\Product\SlaveForm\resource.h</element_pn>
</Row>
<Row>
<element_pn>\leds\代码\Product\SlaveForm\Script1.aps</element_pn>
</Row>
<Row>
<element_pn>\leds\代码\Product\SlaveForm\Script1.rc</element_pn>
</Row>
<Row>
<element_pn>\leds\代码\Product\SlaveForm\SetWndPositionDlg.cpp</element_pn>
</Row>
<Row>
<element_pn>\leds\代码\Product\SlaveForm\SetWndPositionDlg.h</element_pn>
</Row>
<Row>
<element_pn>\leds\代码\Product\SlaveForm\SlaveComm.h</element_pn>
</Row>
<Row>
<element_pn>\leds\代码\Product\SlaveForm\SlavewndPro.cpp</element_pn>
</Row>
<Row>
<element_pn>\leds\代码\Product\SlaveForm\SlaveWndPro.h</element_pn>
</Row>
<Row>
<element_pn>\leds\代码\Product\SlaveForm\StdAfx.cpp</element_pn>
</Row>
<Row>
<element_pn>\leds\代码\Product\SlaveForm\StdAfx.h</element_pn>
</Row>
<Row>
<element_pn>\leds\代码\Product\SlaveForm\SVIDEOPROGRAM.tpm</element_pn>
</Row>
<Row>
<element_pn>\leds\代码\Product\SlaveForm\test.tpm</element_pn>
</Row>
<Row>
<element_pn>\leds\代码\Product\SlaveForm\vssver.scc</element_pn>
</Row>
<Row>
<element_pn>\leds\代码\Product\SlaveForm\WLogRecordset.cpp</element_pn>
</Row>
<Row>
<element_pn>\leds\代码\Product\SlaveForm\WLogRecordset.h</element_pn>
</Row>
<Row>
<element_pn>\leds\代码\Product\SlaveForm\系统图标.ico</element_pn>
</Row>
<Row>
<element_pn>\leds\代码\Resouce</element_pn>
</Row>
<Row>
<element_pn>\leds\代码\Resouce\新建 文本文档.txt</element_pn>
</Row>
<Row>
<element_pn>\leds\代码\UI_AutoCode</element_pn>
</Row>
<Row>
<element_pn>\leds\代码\UI_AutoCode\Leds</element_pn>
</Row>
<Row>
<element_pn>\leds\代码\UI_AutoCode\Leds\Debug</element_pn>
</Row>
<Row>
<element_pn>\leds\代码\UI_AutoCode\Leds\Debug\LEDS.exe</element_pn>
</Row>
<Row>
<element_pn>\leds\代码\UI_AutoCode\Leds\default.pln</element_pn>
</Row>
<Row>
<element_pn>\leds\代码\UI_AutoCode\Leds\Global.h</element_pn>
</Row>
<Row>
<element_pn>\leds\代码\UI_AutoCode\Leds\InsertPlayDlg.cpp</element_pn>
</Row>
<Row>
<element_pn>\leds\代码\UI_AutoCode\Leds\InsertPlayDlg.h</element_pn>
</Row>
<Row>
<element_pn>\leds\代码\UI_AutoCode\Leds\LEDS.APS</element_pn>
</Row>
<Row>
<element_pn>\leds\代码\UI_AutoCode\Leds\LEDS.clw</element_pn>
</Row>
<Row>
<element_pn>\leds\代码\UI_AutoCode\Leds\LEDS.cpp</element_pn>
</Row>
<Row>
<element_pn>\leds\代码\UI_AutoCode\Leds\LEDS.dsp</element_pn>
</Row>
<Row>
<element_pn>\leds\代码\UI_AutoCode\Leds\LEDS.dsw</element_pn>
</Row>
<Row>
<element_pn>\leds\代码\UI_AutoCode\Leds\LEDS.h</element_pn>
</Row>
<Row>
<element_pn>\leds\代码\UI_AutoCode\Leds\LEDS.ncb</element_pn>
</Row>
<Row>
<element_pn>\leds\代码\UI_AutoCode\Leds\LEDS.opt</element_pn>
</Row>
<Row>
<element_pn>\leds\代码\UI_AutoCode\Leds\LEDS.plg</element_pn>
</Row>
<Row>
<element_pn>\leds\代码\UI_AutoCode\Leds\LEDS.rc</element_pn>
</Row>
<Row>
<element_pn>\leds\代码\UI_AutoCode\Leds\LEDSDlg.cpp</element_pn>
</Row>
<Row>
<element_pn>\leds\代码\UI_AutoCode\Leds\LEDSDlg.h</element_pn>
</Row>
<Row>
<element_pn>\leds\代码\UI_AutoCode\Leds\mssccprj.scc</element_pn>
</Row>
<Row>
<element_pn>\leds\代码\UI_AutoCode\Leds\ReadMe.txt</element_pn>
</Row>
<Row>
<element_pn>\leds\代码\UI_AutoCode\Leds\res</element_pn>
</Row>
<Row>
<element_pn>\leds\代码\UI_AutoCode\Leds\res\LEDS.ico</element_pn>
</Row>
<Row>
<element_pn>\leds\代码\UI_AutoCode\Leds\res\LEDS.rc2</element_pn>
</Row>
<Row>
<element_pn>\leds\代码\UI_AutoCode\Leds\Resource.h</element_pn>
</Row>
<Row>
<element_pn>\leds\代码\UI_AutoCode\Leds\StdAfx.cpp</element_pn>
</Row>
<Row>
<element_pn>\leds\代码\UI_AutoCode\Leds\StdAfx.h</element_pn>
</Row>
<Row>
<element_pn>\leds\代码\UI_AutoCode\Leds\test.tpm</element_pn>
</Row>
<Row>
<element_pn>\leds\代码\UI_AutoCode\Make Program Menu</element_pn>
</Row>
<Row>
<element_pn>\leds\代码\UI_AutoCode\Make Program Menu\Debug</element_pn>
</Row>
<Row>
<element_pn>\leds\代码\UI_AutoCode\Make Program Menu\Debug\MakeProPlan.exe</element_pn>
</Row>
<Row>
<element_pn>\leds\代码\UI_AutoCode\Make Program Menu\MakeProPlan.aps</element_pn>
</Row>
<Row>
<element_pn>\leds\代码\UI_AutoCode\Make Program Menu\MakeProPlan.clw</element_pn>
</Row>
<Row>
<element_pn>\leds\代码\UI_AutoCode\Make Program Menu\MakeProPlan.cpp</element_pn>
</Row>
<Row>
<element_pn>\leds\代码\UI_AutoCode\Make Program Menu\MakeProPlan.dsp</element_pn>
</Row>
<Row>
<element_pn>\leds\代码\UI_AutoCode\Make Program Menu\MakeProPlan.dsw</element_pn>
</Row>
<Row>
<element_pn>\leds\代码\UI_AutoCode\Make Program Menu\MakeProPlan.h</element_pn>
</Row>
<Row>
<element_pn>\leds\代码\UI_AutoCode\Make Program Menu\MakeProPlan.ncb</element_pn>
</Row>
<Row>
<element_pn>\leds\代码\UI_AutoCode\Make Program Menu\MakeProPlan.opt</element_pn>
</Row>
<Row>
<element_pn>\leds\代码\UI_AutoCode\Make Program Menu\MakeProPlan.plg</element_pn>
</Row>
<Row>
<element_pn>\leds\代码\UI_AutoCode\Make Program Menu\MakeProPlan.rc</element_pn>
</Row>
<Row>
<element_pn>\leds\代码\UI_AutoCode\Make Program Menu\MakeProPlanDlg.cpp</element_pn>
</Row>
<Row>
<element_pn>\leds\代码\UI_AutoCode\Make Program Menu\MakeProPlanDlg.h</element_pn>
</Row>
<Row>
<element_pn>\leds\代码\UI_AutoCode\Make Program Menu\mssccprj.scc</element_pn>
</Row>
<Row>
<element_pn>\leds\代码\UI_AutoCode\Make Program Menu\PlayandPlan</element_pn>
</Row>
<Row>
<element_pn>\leds\代码\UI_AutoCode\Make Program Menu\PlayItemDlg.cpp</element_pn>
</Row>
<Row>
<element_pn>\leds\代码\UI_AutoCode\Make Program Menu\PlayItemDlg.h</element_pn>
</Row>
<Row>
<element_pn>\leds\代码\UI_AutoCode\Make Program Menu\ReadMe.txt</element_pn>
</Row>
<Row>
<element_pn>\leds\代码\UI_AutoCode\Make Program Menu\res</element_pn>
</Row>
<Row>
<element_pn>\leds\代码\UI_AutoCode\Make Program Menu\res\MakeProPlan.ico</element_pn>
</Row>
<Row>
<element_pn>\leds\代码\UI_AutoCode\Make Program Menu\res\MakeProPlan.rc2</element_pn>
</Row>
<Row>
<element_pn>\leds\代码\UI_AutoCode\Make Program Menu\resource.h</element_pn>
</Row>
<Row>
<element_pn>\leds\代码\UI_AutoCode\Make Program Menu\StdAfx.cpp</element_pn>
</Row>
<Row>
<element_pn>\leds\代码\UI_AutoCode\Make Program Menu\StdAfx.h</element_pn>
</Row>
<Row>
<element_pn>\leds\代码\UI_AutoCode\Manage Playing Plan</element_pn>
</Row>
<Row>
<element_pn>\leds\代码\UI_AutoCode\Manage Playing Plan\AddProgramDlg.cpp</element_pn>
</Row>
<Row>
<element_pn>\leds\代码\UI_AutoCode\Manage Playing Plan\AddProgramDlg.h</element_pn>
</Row>
<Row>
<element_pn>\leds\代码\UI_AutoCode\Manage Playing Plan\BLUR24.AVI</element_pn>
</Row>
<Row>
<element_pn>\leds\代码\UI_AutoCode\Manage Playing Plan\Debug</element_pn>
</Row>
<Row>
<element_pn>\leds\代码\UI_AutoCode\Manage Playing Plan\Debug\MakePM.exe</element_pn>
</Row>
<Row>
<element_pn>\leds\代码\UI_AutoCode\Manage Playing Plan\default.tpm</element_pn>
</Row>
<Row>
<element_pn>\leds\代码\UI_AutoCode\Manage Playing Plan\DelProgramDialog.cpp</element_pn>
</Row>
<Row>
<element_pn>\leds\代码\UI_AutoCode\Manage Playing Plan\DelProgramDialog.h</element_pn>
</Row>
<Row>
<element_pn>\leds\代码\UI_AutoCode\Manage Playing Plan\EditDialog.cpp</element_pn>
</Row>
<Row>
<element_pn>\leds\代码\UI_AutoCode\Manage Playing Plan\EditDialog.h</element_pn>
</Row>
<Row>
<element_pn>\leds\代码\UI_AutoCode\Manage Playing Plan\EndPlayNotifyWnd.cpp</element_pn>
</Row>
<Row>
<element_pn>\leds\代码\UI_AutoCode\Manage Playing Plan\EndPlayNotifyWnd.h</element_pn>
</Row>
<Row>
<element_pn>\leds\代码\UI_AutoCode\Manage Playing Plan\GLOBE.AVI</element_pn>
</Row>
<Row>
<element_pn>\leds\代码\UI_AutoCode\Manage Playing Plan\MainFrm.cpp</element_pn>
</Row>
<Row>
<element_pn>\leds\代码\UI_AutoCode\Manage Playing Plan\MainFrm.h</element_pn>
</Row>
<Row>
<element_pn>\leds\代码\UI_AutoCode\Manage Playing Plan\MakePM.aps</element_pn>
</Row>
<Row>
<element_pn>\leds\代码\UI_AutoCode\Manage Playing Plan\MakePM.clw</element_pn>
</Row>
<Row>
<element_pn>\leds\代码\UI_AutoCode\Manage Playing Plan\MakePM.cpp</element_pn>
</Row>
<Row>
<element_pn>\leds\代码\UI_AutoCode\Manage Playing Plan\MakePM.dsp</element_pn>
</Row>
<Row>
<element_pn>\leds\代码\UI_AutoCode\Manage Playing Plan\MakePM.dsw</element_pn>
</Row>
<Row>
<element_pn>\leds\代码\UI_AutoCode\Manage Playing Plan\MakePM.h</element_pn>
</Row>
<Row>
<element_pn>\leds\代码\UI_AutoCode\Manage Playing Plan\MakePM.ncb</element_pn>
</Row>
<Row>
<element_pn>\leds\代码\UI_AutoCode\Manage Playing Plan\MakePM.opt</element_pn>
</Row>
<Row>
<element_pn>\leds\代码\UI_AutoCode\Manage Playing Plan\MakePM.plg</element_pn>
</Row>
<Row>
<element_pn>\leds\代码\UI_AutoCode\Manage Playing Plan\MakePM.rc</element_pn>
</Row>
<Row>
<element_pn>\leds\代码\UI_AutoCode\Manage Playing Plan\MakePMDoc.cpp</element_pn>
</Row>
<Row>
<element_pn>\leds\代码\UI_AutoCode\Manage Playing Plan\MakePMDoc.h</element_pn>
</Row>
<Row>
<element_pn>\leds\代码\UI_AutoCode\Manage Playing Plan\MakePMView.cpp</element_pn>
</Row>
<Row>
<element_pn>\leds\代码\UI_AutoCode\Manage Playing Plan\MakePMView.h</element_pn>
</Row>
<Row>
<element_pn>\leds\代码\UI_AutoCode\Manage Playing Plan\MakeProgramMenuForm.cpp</element_pn>
</Row>
<Row>
<element_pn>\leds\代码\UI_AutoCode\Manage Playing Plan\MakeProgramMenuForm.h</element_pn>
</Row>
<Row>
<element_pn>\leds\代码\UI_AutoCode\Manage Playing Plan\mssccprj.scc</element_pn>
</Row>
<Row>
<element_pn>\leds\代码\UI_AutoCode\Manage Playing Plan\ProgramMenuForMake.cpp</element_pn>
</Row>
<Row>
<element_pn>\leds\代码\UI_AutoCode\Manage Playing Plan\ProgramMenuForMake.h</element_pn>
</Row>
<Row>
<element_pn>\leds\代码\UI_AutoCode\Manage Playing Plan\ReadMe.txt</element_pn>
</Row>
<Row>
<element_pn>\leds\代码\UI_AutoCode\Manage Playing Plan\Release</element_pn>
</Row>
<Row>
<element_pn>\leds\代码\UI_AutoCode\Manage Playing Plan\Release\MakePM.exe</element_pn>
</Row>
<Row>
<element_pn>\leds\代码\UI_AutoCode\Manage Playing Plan\res</element_pn>
</Row>
<Row>
<element_pn>\leds\代码\UI_AutoCode\Manage Playing Plan\res\MakePM.ico</element_pn>
</Row>
<Row>
<element_pn>\leds\代码\UI_AutoCode\Manage Playing Plan\res\MakePM.rc2</element_pn>
</Row>
<Row>
<element_pn>\leds\代码\UI_AutoCode\Manage Playing Plan\res\MakePMDoc.ico</element_pn>
</Row>
<Row>
<element_pn>\leds\代码\UI_AutoCode\Manage Playing Plan\res\Toolbar.bmp</element_pn>
</Row>
<Row>
<element_pn>\leds\代码\UI_AutoCode\Manage Playing Plan\Resource.h</element_pn>
</Row>
<Row>
<element_pn>\leds\代码\UI_AutoCode\Manage Playing Plan\StdAfx.cpp</element_pn>
</Row>
<Row>
<element_pn>\leds\代码\UI_AutoCode\Manage Playing Plan\StdAfx.h</element_pn>
</Row>
<Row>
<element_pn>\leds\代码\UI_AutoCode\Manage Playing Plan\trip.swf</element_pn>
</Row>
<Row>
<element_pn>\leds\代码\单元测试</element_pn>
</Row>
<Row>
<element_pn>\leds\代码\单元测试\CManageSystemForm.doc</element_pn>
</Row>
<Row>
<element_pn>\leds\代码\单元测试\LEDS-TEST-SST-UTC-CConnectControl.doc</element_pn>
</Row>
<Row>
<element_pn>\leds\代码\单元测试\LEDS-TEST-SST-UTC-CConnectForm.doc</element_pn>
</Row>
<Row>
<element_pn>\leds\代码\单元测试\LEDS-TEST-SST-UTC-CLEDClientData.doc</element_pn>
</Row>
<Row>
<element_pn>\leds\代码\单元测试\LEDS-TEST-SST-UTC-CLoginDialog.doc</element_pn>
</Row>
<Row>
<element_pn>\leds\代码\单元测试\LEDS-TEST-SST-UTC-CUserData.doc</element_pn>
</Row>
<Row>
<element_pn>\leds\代码\单元测试\LEDS.cfy</element_pn>
</Row>
<Row>
<element_pn>\leds\代码\单元测试\Test Evaluation Summary.doc</element_pn>
</Row>
<Row>
<element_pn>\leds\代码\单元测试\单元测试评估报告评审记录.doc</element_pn>
</Row>
<Row>
<element_pn>\leds\配置管理</element_pn>
</Row>
<Row>
<element_pn>\leds\配置管理\报告</element_pn>
</Row>
<Row>
<element_pn>\leds\配置管理\报告\Configuration State Accounting.doc</element_pn>
</Row>
<Row>
<element_pn>\leds\配置管理\变更</element_pn>
</Row>
<Row>
<element_pn>\leds\配置管理\变更\CR-SDP-1029.doc</element_pn>
</Row>
<Row>
<element_pn>\leds\配置管理\变更\CR_1008-1.doc</element_pn>
</Row>
<Row>
<element_pn>\leds\配置管理\变更\CR_1008-2.doc</element_pn>
</Row>
<Row>
<element_pn>\leds\配置管理\变更\CR_1010-1.doc</element_pn>
</Row>
<Row>
<element_pn>\leds\配置管理\变更\CR_1011-1.doc</element_pn>
</Row>
<Row>
<element_pn>\leds\配置管理\变更\CR_1012-1.doc</element_pn>
</Row>
<Row>
<element_pn>\leds\配置管理\变更\CR_1024-1.doc</element_pn>
</Row>
<Row>
<element_pn>\leds\配置管理\变更\CR_1026-1.doc</element_pn>
</Row>
<Row>
<element_pn>\leds\配置管理\变更\CR_1029-1.doc</element_pn>
</Row>
<Row>
<element_pn>\leds\配置管理\计划</element_pn>
</Row>
<Row>
<element_pn>\leds\配置管理\计划\Configuration Management Plan.doc</element_pn>
</Row>
<Row>
<element_pn>\leds\配置管理\配置项发布</element_pn>
</Row>
<Row>
<element_pn>\leds\配置管理\配置项发布\B20.xml</element_pn>
</Row>
<Row>
<element_pn>\leds\配置管理\配置项发布\table.xsl</element_pn>
</Row>
<Row>
<element_pn>\leds\评审</element_pn>
</Row>
<Row>
<element_pn>\leds\评审\PL_DMDC1_1026.zip</element_pn>
</Row>
<Row>
<element_pn>\leds\评审\PL_DMDC2_1029.zip</element_pn>
</Row>
<Row>
<element_pn>\leds\评审\PR_TES_1106.doc</element_pn>
</Row>
<Row>
<element_pn>\leds\评审\第二阶段(精化)评审记录表.doc</element_pn>
</Row>
<Row>
<element_pn>\leds\评审\第一阶段(先启)评审记录表.doc</element_pn>
</Row>
<Row>
<element_pn>\leds\评审\评审记录表.doc</element_pn>
</Row>
<Row>
<element_pn>\leds\设计与实施</element_pn>
</Row>
<Row>
<element_pn>\leds\设计与实施\文档</element_pn>
</Row>
<Row>
<element_pn>\leds\设计与实施\文档\Integration Build Plan.doc</element_pn>
</Row>
<Row>
<element_pn>\leds\设计与实施\文档\LEDS-SAD.doc</element_pn>
</Row>
<Row>
<element_pn>\leds\设计与实施\文档\LEDS-SCAD.doc</element_pn>
</Row>
<Row>
<element_pn>\leds\设计与实施\文档\UI Guideline.doc</element_pn>
</Row>
<Row>
<element_pn>\leds\设计与实施\文档\错误处理机制.doc</element_pn>
</Row>
<Row>
<element_pn>\leds\设计与实施\文档\数据永久性机制描述1.doc</element_pn>
</Row>
<Row>
<element_pn>\leds\设计与实施\文档\通信机制描述.doc</element_pn>
</Row>
<Row>
<element_pn>\leds\项目管理</element_pn>
</Row>
<Row>
<element_pn>\leds\项目管理\计划</element_pn>
</Row>
<Row>
<element_pn>\leds\项目管理\计划\Iteration Plan in Inception.mpp</element_pn>
</Row>
<Row>
<element_pn>\leds\项目管理\计划\LEDS-(Elaboration) Iteration Plan.doc</element_pn>
</Row>
<Row>
<element_pn>\leds\项目管理\计划\LEDS-(Inception) Iteration Plan.doc</element_pn>
</Row>
<Row>
<element_pn>\leds\项目管理\计划\LEDS-Consturction Iteration Plan.doc</element_pn>
</Row>
<Row>
<element_pn>\leds\项目管理\计划\LEDS-Problem Resolution Plan.doc</element_pn>
</Row>
<Row>
<element_pn>\leds\项目管理\计划\LEDS-Project Risk List.doc</element_pn>
</Row>
<Row>
<element_pn>\leds\项目管理\计划\LEDS-Requirements Management Plan.doc</element_pn>
</Row>
<Row>
<element_pn>\leds\项目管理\计划\LEDS-Risk Management Plan.dot</element_pn>
</Row>
<Row>
<element_pn>\leds\项目管理\计划\LEDS-Software Development Plan.doc</element_pn>
</Row>
<Row>
<element_pn>\leds\项目管理\计划\working sheet20011013.mpp</element_pn>
</Row>
<Row>
<element_pn>\leds\项目管理\计划\working sheet20011022.mpp</element_pn>
</Row>
<Row>
<element_pn>\leds\项目管理\计划\working sheet20011026.mpp</element_pn>
</Row>
<Row>
<element_pn>\leds\项目管理\计划\working sheet20011102.mpp</element_pn>
</Row>
<Row>
<element_pn>\leds\项目管理\评估</element_pn>
</Row>
<Row>
<element_pn>\leds\项目管理\评估\LEDS-(Elaboration) Iteration Assessment.doc</element_pn>
</Row>
<Row>
<element_pn>\leds\项目管理\评估\LEDS-Construction Status Assessment.doc</element_pn>
</Row>
<Row>
<element_pn>\leds\项目管理\评估\LEDS-Elaboration Status Assessment.doc</element_pn>
</Row>
<Row>
<element_pn>\leds\项目管理\评估\LEDS-Inception Status Assessment.doc</element_pn>
</Row>
<Row>
<element_pn>\leds\项目管理\评估\表4：项目进度跟踪表20010826.doc</element_pn>
</Row>
<Row>
<element_pn>\leds\项目管理\评估\表4：项目进度跟踪表20010901.doc</element_pn>
</Row>
<Row>
<element_pn>\leds\项目管理\评估\表4：项目进度跟踪表20010908.doc</element_pn>
</Row>
<Row>
<element_pn>\leds\项目管理\评估\表4：项目进度跟踪表20010914.doc</element_pn>
</Row>
<Row>
<element_pn>\leds\项目管理\评估\表4：项目进度跟踪表20010929.doc</element_pn>
</Row>
<Row>
<element_pn>\leds\项目管理\评估\表4：项目进度跟踪表20011013.doc</element_pn>
</Row>
<Row>
<element_pn>\leds\项目管理\评估\表4：项目进度跟踪表20011022.doc</element_pn>
</Row>
<Row>
<element_pn>\leds\项目管理\评估\表4：项目进度跟踪表20011026.doc</element_pn>
</Row>
<Row>
<element_pn>\leds\项目管理\评估\表4：项目进度跟踪表20011102.doc</element_pn>
</Row>
<Row>
<element_pn>\leds\需求</element_pn>
</Row>
<Row>
<element_pn>\leds\需求\报告</element_pn>
</Row>
<Row>
<element_pn>\leds\需求\报告\LEDS-REQ-Status-Report.doc</element_pn>
</Row>
<Row>
<element_pn>\leds\需求\模型</element_pn>
</Row>
<Row>
<element_pn>\leds\需求\模型\LEDS.mdl</element_pn>
</Row>
<Row>
<element_pn>\leds\需求\数据库</element_pn>
</Row>
<Row>
<element_pn>\leds\需求\数据库\LEDS( S054-06-2001).MDB</element_pn>
</Row>
<Row>
<element_pn>\leds\需求\数据库\LEDS( S054-06-2001).RQS</element_pn>
</Row>
<Row>
<element_pn>\leds\需求\数据库\PROJ_PRD.SS</element_pn>
</Row>
<Row>
<element_pn>\leds\需求\数据库\PROJ_SRS.FEAT</element_pn>
</Row>
<Row>
<element_pn>\leds\需求\数据库\UC 用例属性.CSV</element_pn>
</Row>
<Row>
<element_pn>\leds\需求\文档</element_pn>
</Row>
<Row>
<element_pn>\leds\需求\文档\Glossary.doc</element_pn>
</Row>
<Row>
<element_pn>\leds\需求\文档\LEDS-Development Case.doc</element_pn>
</Row>
<Row>
<element_pn>\leds\需求\文档\LEDS-Stakeholder Requests.doc</element_pn>
</Row>
<Row>
<element_pn>\leds\需求\文档\LEDS-Supplementary Specification.doc</element_pn>
</Row>
<Row>
<element_pn>\leds\需求\文档\LEDS-Vision.doc</element_pn>
</Row>
<Row>
<element_pn>\leds\需求\文档\TPUP_CostEstimationModel.xls</element_pn>
</Row>
<Row>
<element_pn>\leds\需求\文档\UCS-Configure LED.doc</element_pn>
</Row>
<Row>
<element_pn>\leds\需求\文档\UCS-Connect LED.doc</element_pn>
</Row>
<Row>
<element_pn>\leds\需求\文档\UCS-Control Play.doc</element_pn>
</Row>
<Row>
<element_pn>\leds\需求\文档\UCS-Inform Status.doc</element_pn>
</Row>
<Row>
<element_pn>\leds\需求\文档\UCS-Insert Playing.doc</element_pn>
</Row>
<Row>
<element_pn>\leds\需求\文档\UCS-Login.doc</element_pn>
</Row>
<Row>
<element_pn>\leds\需求\文档\UCS-Make Dynamic Datamation.doc</element_pn>
</Row>
<Row>
<element_pn>\leds\需求\文档\UCS-Make Program Menu.doc</element_pn>
</Row>
<Row>
<element_pn>\leds\需求\文档\UCS-Manage LED State.doc</element_pn>
</Row>
<Row>
<element_pn>\leds\需求\文档\UCS-Manage Playing Log.doc</element_pn>
</Row>
<Row>
<element_pn>\leds\需求\文档\UCS-Manage Playing Plan .doc</element_pn>
</Row>
<Row>
<element_pn>\leds\需求\文档\UCS-Manage System.doc</element_pn>
</Row>
<Row>
<element_pn>\leds\需求\文档\UCS-Manage Wrong Log.doc</element_pn>
</Row>
<Row>
<element_pn>\leds\需求\文档\UCS-Preview Program Menu.doc</element_pn>
</Row>
<Row>
<element_pn>\leds\需求\文档\UCS-Time Control.doc</element_pn>
</Row>
<Row>
<element_pn>\leds\需求\文档\UCS-Time Playing.doc</element_pn>
</Row>
</Report>
